{"4608": ["ufmg01"], "513": ["ufmg01"], "25091": ["amsterdam01"], "57264": ["ufmg01"], "13830": ["ufmg01"], "53767": ["ufmg01"], "49673": ["amsterdam01"], "57866": ["amsterdam01"], "6667": ["amsterdam01"], "196621": ["amsterdam01"], "59919": ["amsterdam01"], "12307": ["amsterdam01"], "206356": ["amsterdam01"], "59414": ["amsterdam01"], "56665": ["amsterdam01"], "14361": ["amsterdam01"], "8218": ["amsterdam01"], "7195": ["ufmg01"], "8220": ["amsterdam01"], "8222": ["amsterdam01"], "49697": ["amsterdam01"], "20514": ["amsterdam01"], "57381": ["amsterdam01"], "34854": ["amsterdam01"], "553": ["amsterdam01"], "47147": ["amsterdam01"], "1280": ["ufmg01"], "12637": ["amsterdam01"], "7713": ["amsterdam01"], "2613": ["amsterdam01"], "8758": ["amsterdam01"], "34872": ["amsterdam01"], "30132": ["amsterdam01"], "3130": ["ufmg01"], "16735": ["ufmg01"], "28220": ["ufmg01"], "12350": ["amsterdam01"], "25152": ["amsterdam01"], "34224": ["amsterdam01"], "23106": ["ufmg01"], "204355": ["amsterdam01"], "53828": ["ufmg01"], "57199": ["ufmg01"], "25160": ["amsterdam01"], "15435": ["amsterdam01"], "264268": ["ufmg01"], "59469": ["amsterdam01"], "1103": ["amsterdam01"], "31313": ["amsterdam01"], "20562": ["amsterdam01"], "4181": ["amsterdam01"], "36351": ["amsterdam01"], "9304": ["amsterdam01"], "8283": ["amsterdam01"], "37468": ["amsterdam01"], "37989": ["amsterdam01"], "28260": ["ufmg01"], "262757": ["ufmg01"], "137831": ["amsterdam01"], "2152": ["ufmg01"], "210025": ["amsterdam01"], "6762": ["amsterdam01"], "39533": ["amsterdam01"], "50877": ["amsterdam01"], "20080": ["ufmg01"], "38001": ["amsterdam01"], "3277": ["amsterdam01"], "206499": ["amsterdam01"], "1140": ["amsterdam01"], "57463": ["amsterdam01"], "28792": ["amsterdam01"], "45177": ["ufmg01"], "22652": ["amsterdam01"], "202365": ["amsterdam01"], "52863": ["ufmg01", "amsterdam01"], "50304": ["amsterdam01"], "8896": ["amsterdam01"], "4739": ["amsterdam01"], "20612": ["amsterdam01"], "41095": ["amsterdam01"], "52873": ["ufmg01"], "25227": ["amsterdam01"], "42473": ["ufmg01", "amsterdam01"], "58511": ["amsterdam01"], "12859": ["amsterdam01"], "3267": ["amsterdam01"], "58308": ["amsterdam01"], "209263": ["amsterdam01"], "28186": ["ufmg01"], "15008": ["amsterdam01"], "51873": ["amsterdam01"], "29467": ["amsterdam01"], "7575": ["ufmg01", "amsterdam01"], "680": ["ufmg01"], "4777": ["ufmg01"], "174": ["ufmg01"], "48821": ["amsterdam01"], "3257": ["amsterdam01"], "18106": ["amsterdam01"], "15547": ["amsterdam01"], "6720": ["amsterdam01"], "701": ["ufmg01"], "31424": ["amsterdam01"], "51907": ["amsterdam01"], "207044": ["amsterdam01"], "1221": ["amsterdam01"], "37497": ["amsterdam01"], "58057": ["ufmg01", "amsterdam01"], "15562": ["amsterdam01"], "51405": ["amsterdam01"], "264911": ["ufmg01"], "39120": ["amsterdam01"], "39122": ["amsterdam01"], "42275": ["amsterdam01"], "59605": ["amsterdam01"], "23673": ["amsterdam01"], "132825": ["ufmg01"], "4826": ["amsterdam01"], "19151": ["ufmg01"], "393950": ["amsterdam01"], "5413": ["amsterdam01"], "6881": ["amsterdam01"], "34019": ["amsterdam01"], "29222": ["amsterdam01"], "13030": ["ufmg01", "amsterdam01"], "3303": ["amsterdam01"], "50300": ["amsterdam01"], "8426": ["amsterdam01"], "37100": ["amsterdam01"], "14061": ["ufmg01", "amsterdam01"], "6894": ["ufmg01"], "21232": ["amsterdam01"], "198385": ["amsterdam01"], "34549": ["amsterdam01"], "267613": ["ufmg01"], "28917": ["amsterdam01"], "29680": ["ufmg01"], "35369": ["amsterdam01"], "29140": ["amsterdam01"], "41722": ["amsterdam01"], "204028": ["amsterdam01"], "19754": ["amsterdam01"], "209152": ["amsterdam01"], "328320": ["amsterdam01"], "31019": ["amsterdam01"], "3333": ["amsterdam01"], "1798": ["ufmg01"], "8455": ["amsterdam01"], "1239": ["amsterdam01"], "49420": ["amsterdam01"], "64271": ["ufmg01", "amsterdam01"], "5392": ["amsterdam01"], "11537": ["amsterdam01"], "1299": ["amsterdam01"], "5396": ["amsterdam01"], "53013": ["ufmg01"], "6423": ["amsterdam01"], "49432": ["amsterdam01"], "25220": ["amsterdam01"], "6939": ["amsterdam01"], "20764": ["amsterdam01"], "28634": ["ufmg01"], "286": ["amsterdam01"], "395152": ["amsterdam01"], "35619": ["ufmg01"], "293": ["ufmg01"], "14630": ["amsterdam01"], "29479": ["amsterdam01"], "59689": ["amsterdam01"], "9002": ["amsterdam01"], "24875": ["amsterdam01"], "8492": ["amsterdam01"], "204526": ["amsterdam01"], "6453": ["amsterdam01"], "27446": ["ufmg01"], "204092": ["amsterdam01"], "17639": ["amsterdam01"], "29504": ["ufmg01"], "59715": ["amsterdam01"], "19782": ["ufmg01"], "1351": ["ufmg01"], "57111": ["amsterdam01"], "20811": ["amsterdam01"], "7500": ["ufmg01"], "25933": ["ufmg01"], "47950": ["amsterdam01"], "2895": ["amsterdam01"], "34177": ["amsterdam01"], "47441": ["amsterdam01"], "38883": ["amsterdam01"], "852": ["amsterdam01"], "49788": ["amsterdam01"], "397143": ["amsterdam01"], "37721": ["amsterdam01"], "43578": ["amsterdam01"], "57695": ["ufmg01", "amsterdam01"], "32097": ["amsterdam01"], "2914": ["ufmg01", "amsterdam01"], "14907": ["amsterdam01"], "34800": ["ufmg01"], "7018": ["ufmg01"], "49515": ["amsterdam01"], "198290": ["amsterdam01"], "41327": ["amsterdam01"], "43376": ["amsterdam01"], "37239": ["amsterdam01"], "24441": ["amsterdam01"], "1403": ["amsterdam01"], "1916": ["ufmg01"], "6082": ["ufmg01"], "24961": ["amsterdam01"], "263047": ["ufmg01"], "6539": ["amsterdam01"], "36236": ["amsterdam01"], "39821": ["amsterdam01"], "20205": ["amsterdam01"], "51088": ["amsterdam01"], "131477": ["ufmg01"], "205206": ["amsterdam01"], "37271": ["amsterdam01"], "56730": ["amsterdam01"], "28571": ["ufmg01"], "8607": ["amsterdam01"], "263152": ["ufmg01"], "24482": ["ufmg01", "amsterdam01"], "263075": ["ufmg01"], "53070": ["ufmg01"], "38726": ["ufmg01"], "11686": ["ufmg01"], "51185": ["ufmg01", "amsterdam01"], "55720": ["amsterdam01"], "16347": ["amsterdam01"], "3741": ["amsterdam01"], "20912": ["ufmg01"], "61595": ["ufmg01"], "13237": ["amsterdam01"], "39351": ["amsterdam01"], "58299": ["amsterdam01"], "11708": ["amsterdam01"], "15605": ["amsterdam01"], "2497": ["ufmg01"], "35266": ["amsterdam01"], "50763": ["amsterdam01"], "20932": ["amsterdam01"], "49605": ["amsterdam01"], "54728": ["amsterdam01"], "47692": ["amsterdam01"], "34288": ["amsterdam01"], "64463": ["ufmg01"], "328145": ["ufmg01"], "202194": ["amsterdam01"], "3491": ["amsterdam01"], "63956": ["amsterdam01"], "206313": ["amsterdam01"], "2518": ["ufmg01"], "26073": ["amsterdam01"], "13786": ["amsterdam01"], "64475": ["amsterdam01"], "3549": ["ufmg01"], "38880": ["amsterdam01"], "5602": ["amsterdam01"], "263651": ["ufmg01"], "3561": ["ufmg01"], "12779": ["amsterdam01"], "7660": ["ufmg01"], "49134": ["amsterdam01"], "52720": ["ufmg01"], "50673": ["amsterdam01"], "59891": ["amsterdam01"], "29686": ["amsterdam01"], "28329": ["ufmg01"], "14840": ["ufmg01"], "263508": ["ufmg01"], "263674": ["ufmg01"], "29691": ["amsterdam01"], "24516": ["amsterdam01"], "31742": ["ufmg01"], "60501": ["amsterdam01"]}